ReIDManager.py
__init__.py
containers/ReIDTracker.py
containers/__init__.py
reidmanager-0.1.1.dist-info/LICENSE
reidmanager-0.1.1.dist-info/METADATA
reidmanager-0.1.1.dist-info/WHEEL
reidmanager-0.1.1.dist-info/top_level.txt
reidmanager-0.1.1.dist-info/RECORD
