Metadata-Version: 2.1
Name: reidmanager
Version: 0.1.1
Summary: An ReID packaged to extract IDs based on features
Author-email: Luís Felipe Milczarek Quadros <luis.milczarek@furg.br>
Project-URL: Homepage, https://github.com/LuisMilczarek/ReIDManager
Project-URL: Issues, https://github.com/LuisMilczarek/ReIDManager/issues
Classifier: Programming Language :: Python :: 3
Classifier: License :: OSI Approved :: MIT License
Classifier: Operating System :: OS Independent
Requires-Python: >=3.8
License-File: LICENSE
Requires-Dist: torchreid >=1.4
Requires-Dist: numpy
